README.md
setup.py
easydl/__init__.py
easydl.egg-info/PKG-INFO
easydl.egg-info/SOURCES.txt
easydl.egg-info/dependency_links.txt
easydl.egg-info/entry_points.txt
easydl.egg-info/not-zip-safe
easydl.egg-info/requires.txt
easydl.egg-info/top_level.txt
easydl/common/__init__.py
easydl/common/commands.py
easydl/common/datasets.py
easydl/common/gpuutils.py
easydl/common/scheduler.py
easydl/common/visualization.py
easydl/common/wheel.py
easydl/pytorch/__init__.py
easydl/pytorch/utils.py
easydl/tf/__init__.py
easydl/tf/evaluation.py
easydl/tf/summary.py
easydl/tf/wheel.py