Metadata-Version: 1.0
Name: easydl
Version: 2.2.0
Summary: "more powerful runTask"
Home-page: https://github.com/thuml/easydl
Author: UNKNOWN
Author-email: UNKNOWN
License: MIT
Platform: UNKNOWN
